Workbook
Name Z_578704EF_7FEB_466F_8696_9E38F7D13393_.wvu.Cols: Planejamento!$M:$IM
Name Z_578704EF_7FEB_466F_8696_9E38F7D13393_.wvu.Cols: Proposta!$I:$IX
Name Z_578704EF_7FEB_466F_8696_9E38F7D13393_.wvu.PrintArea: Planejamento!$B$2:$H$51
Name Z_578704EF_7FEB_466F_8696_9E38F7D13393_.wvu.PrintArea: Proposta!$A$2:$H$201

Sheet Proposta
G2: =TODAY() -> 45850 | H2: 4ª Proposta
G4: Cliente: | H4: Marlisson
G5: Proposta: | H5: 20250520
B8: DOCUMENTOS E EXIGÊNCIAS LEGAIS | F8: =H8*100/(G199) -> 3.6068813 | G8: % | H8: =SUM(H12:H16) -> 1032.3124
E10: m² | ml | unid. | F10: quant.
B12: =Planejamento!B3 -> Projeto Arquitetonito para Liberação da Obra | E12: =Planejamento!C3 -> m² | F12: =Planejamento!D3 -> 0 | H12: =Planejamento!N3 -> 0
B14: =Planejamento!B4 -> Anotação de Responsabilidade Técnica (RRT) | E14: =Planejamento!C4 -> m² | F14: =Planejamento!D4 -> 36 | H14: =Planejamento!N4 -> 1032.3124
B15: =Planejamento!B5 -> Impressões | E15: =Planejamento!C5 -> unidade | F15: =Planejamento!D5 -> 0 | H15: =Planejamento!N5 -> 0
B16: =Planejamento!B6 -> Seguro de Obra | E16: =Planejamento!C6 -> m² | F16: =Planejamento!D6 -> 0 | H16: =Planejamento!N6 -> 0
B18: STAFF | F18: =H18*100/(G199) -> 2.9850052 | G18: % | H18: =SUM(H22:H26) -> 854.32752
E20: m² | ml | unid. | F20: quant.
B22: =Planejamento!B7 -> arquiteto | E22: =Planejamento!C7 -> hora | F22: =Planejamento!D7 -> 0 | H22: =Planejamento!N7 -> 0
B23: =Planejamento!B8 -> ajudante | E23: =Planejamento!C8 -> unidade | F23: =Planejamento!D8 -> 0 | H23: =Planejamento!N8 -> 0
B24: =Planejamento!B9 -> encarregado | E24: =Planejamento!C9 -> unidade | F24: =Planejamento!D9 -> 0 | H24: =Planejamento!N9 -> 0
B25: =Planejamento!B10 -> engenheiro | E25: =Planejamento!C10 -> unidade | F25: =Planejamento!D10 -> 0 | H25: =Planejamento!N10 -> 0
B26: =Planejamento!B11 -> limpeza recorrente | E26: =Planejamento!C11 -> unidade | F26: =Planejamento!D11 -> 36 | H26: =Planejamento!N11 -> 854.32752
B28: SERVIÇOS PRELIMINARES | F28: =H28*100/(G199) -> 5.1132034 | G28: % | H28: =SUM(H32:H45) -> 1463.4314
E30: m² | ml | unid. | F30: quant.
B32: =Planejamento!B12 -> saco para entulho* | E32: =Planejamento!C12 -> unidade | F32: =Planejamento!D12 -> 0 | H32: =Planejamento!N12 -> 0
B33: =Planejamento!B13 -> demolição de alvenaria | E33: =Planejamento!C13 -> m² | F33: =Planejamento!D13 -> 0 | H33: =Planejamento!N13 -> 0
B34: =Planejamento!B14 -> demolição e remocação de teto drywall | E34: =Planejamento!C14 -> m² | F34: =Planejamento!D14 -> 0 | H34: =Planejamento!N14 -> 0
B35: =Planejamento!B15 -> equipe para retirada de entulho | E35: =Planejamento!C15 -> unidade | F35: =Planejamento!D15 -> 36 | H35: =Planejamento!N15 -> 1067.9094
B36: =Planejamento!B16 -> caçamba de entulho* | E36: =Planejamento!C16 -> unidade | F36: =Planejamento!D16 -> 0 | H36: =Planejamento!N16 -> 0
B37: =Planejamento!B17 -> remoção de pisos | E37: =Planejamento!C17 -> unidade | F37: =Planejamento!D17 -> 0 | H37: =Planejamento!N17 -> 0
B38: =Planejamento!B18 -> remoção de caxilhos e portas | E38: =Planejamento!C18 -> unidade | F38: =Planejamento!D18 -> 0 | H38: =Planejamento!N18 -> 0
B39: =Planejamento!B19 -> remoções de portas e batentes | E39: =Planejamento!C19 -> unidade | F39: =Planejamento!D19 -> 0 | H39: =Planejamento!N19 -> 0
B40: =Planejamento!B20 -> remoção de bancada de cozinha | E40: =Planejamento!C20 -> unidade | F40: =Planejamento!D20 -> 1 | H40: =Planejamento!N20 -> 197.761
B41: =Planejamento!B21 -> remoção de tanque | E41: =Planejamento!C21 -> unidade | F41: =Planejamento!D21 -> 0 | H41: =Planejamento!N21 -> 0
B42: =Planejamento!B22 -> remoção de bacias sanitárias | E42: =Planejamento!C22 -> unidade | F42: =Planejamento!D22 -> 0 | H42: =Planejamento!N22 -> 0
B43: =Planejamento!B23 -> remoção de torneira | E43: =Planejamento!C23 -> unidade | F43: =Planejamento!D23 -> 0 | H43: =Planejamento!N23 -> 0
... B45: =Planejamento!B25 -> armários com descarte | E45: =Planejamento!C25 -> unidade | F45: =Planejamento!D25 -> 0 | H45: =Planejamento!N25 -> 0
B47: AR CONDICONADO | F47: =H47*100/(G199) -> 13.128495 | G47: % | H47: =SUM(H51:H54) -> 3757.459
E49: m² | ml | unid. | F49: quant.
B51: =Planejamento!B26 -> tubulação para equipamentos de 9 mil a 12 mil btus | E51: =Planejamento!C26 -> ml | F51: =Planejamento!D26 -> 10 | H51: =Planejamento!N26 -> 2768.654
B52: =Planejamento!B27 -> tubulação para equipamentos de 18 mil a 24 mil btus | E52: =Planejamento!C27 -> ml | F52: =Planejamento!D27 -> 0 | H52: =Planejamento!N27 -> 0
B53: =Planejamento!B28 -> drenos | E53: =Planejamento!C28 -> unidade | F53: =Planejamento!D28 -> 1 | H53: =Planejamento!N28 -> 395.522
B54: =Planejamento!B29 -> acoplamento dos equipamentos | E54: =Planejamento!C29 -> unidade | F54: =Planejamento!D29 -> 1 | H54: =Planejamento!N29 -> 593.283
B56: ELÉTRICA | F56: =H56*100/(G199) -> 6.4951502 | G56: % | H56: =SUM(H60:H77) -> 1858.9534
E58: m² | ml | unid. | F58: quant.
B60: =Planejamento!B30 -> alteração de quadro elétrico | E60: =Planejamento!C30 -> unidade | F60: =Planejamento!D30 -> 0 | H60: =Planejamento!N30 -> 0
B61: =Planejamento!B31 -> instalação de balizador | E61: =Planejamento!C41 -> unidade | F61: =Planejamento!D31 -> 0 | H61: =Planejamento!N31 -> 0
B62: =Planejamento!B32 -> instalação de fita de led | E62: =Planejamento!C31 -> unidade | F62: =Planejamento!D32 -> 0 | H62: =Planejamento!N32 -> 0
B63: =Planejamento!B33 -> instalação de luminárias especiais | E63: =Planejamento!C32 -> unidade | F63: =Planejamento!D33 -> 0 | H63: =Planejamento!N33 -> 0
B64: =Planejamento!B34 -> instalação de lustre | E64: =Planejamento!C42 -> unidade | F64: =Planejamento!D34 -> 0 | H64: =Planejamento!N34 -> 0
B65: =Planejamento!B35 -> instalação de pendente | E65: =Planejamento!C33 -> unidade | F65: =Planejamento!D35 -> 0 | H65: =Planejamento!N35 -> 0
B66: =Planejamento!B36 -> interruptor intermediário | E66: =Planejamento!C34 -> unidade | F66: =Planejamento!D36 -> 0 | H66: =Planejamento!N36 -> 0
B67: =Planejamento!B37 -> interruptor paralelo | E67: =Planejamento!C35 -> unidade | F67: =Planejamento!D37 -> 0 | H67: =Planejamento!N37 -> 0
B68: =Planejamento!B38 -> interruptor simples | E68: =Planejamento!C36 -> unidade | F68: =Planejamento!D38 -> 0 | H68: =Planejamento!N38 -> 0
B69: =Planejamento!B39 -> ponto de balizador | E69: =Planejamento!C37 -> unidade | F69: =Planejamento!D39 -> 0 | H69: =Planejamento!N39 -> 0
B70: =Planejamento!B40 -> ponto de energia para motorização | E70: =Planejamento!C38 -> unidade | F70: =Planejamento!D40 -> 0 | H70: =Planejamento!N40 -> 0
B71: =Planejamento!B41 -> furação e recorte para luminárias | E71: =Planejamento!C39 -> unidade | F71: =Planejamento!D41 -> 0 | H71: =Planejamento!N41 -> 0
B72: =Planejamento!B42 -> instalação de luminárias | E72: =Planejamento!C40 -> unidade | F72: =Planejamento!D42 -> 12 | H72: =Planejamento!N42 -> 1186.566
B73: =Planejamento!B43 -> ponto de iluminação | E73: =Planejamento!C43 -> unidade | F73: =Planejamento!D43 -> 2 | H73: =Planejamento!N43 -> 474.6264
B74: =Planejamento!B44 -> ponto de tomada 110v | E74: =Planejamento!C48 -> unidade | F74: =Planejamento!D44 -> 0 | H74: =Planejamento!N44 -> 0
B75: =Planejamento!B45 -> ponto de tomada 220v | E75: =Planejamento!C44 -> unidade | F75: =Planejamento!D45 -> 0 | H75: =Planejamento!N45 -> 0
B76: =Planejamento!B46 -> ponto de tomada 220v circuito independente | E76: =Planejamento!C45 -> unidade | F76: =Planejamento!D46 -> 0 | H76: =Planejamento!N46 -> 0
B77: =Planejamento!B47 -> ponto para led | E77: =Planejamento!C46 -> unidade | F77: =Planejamento!D47 -> 1 | H77: =Planejamento!N47 -> 197.761
B79: AUTOMAÇÃO | F79: =H79*100/(G199) -> 0 | G79: % | H79: =SUM(H83:H91) -> 0
E81: m² | ml | unid. | F81: quant.
B83: =Planejamento!B48 -> ponto de internet | E83: =Planejamento!C48 -> unidade | F83: =Planejamento!D48 -> 0 | H83: =Planejamento!N48 -> 0
B84: =Planejamento!B49 -> ponto de som | E84: =Planejamento!C49 -> unidade | F84: =Planejamento!D49 -> 0 | H84: =Planejamento!N49 -> 0
B85: =Planejamento!B50 -> ponto de wifi | E85: =Planejamento!C50 -> unidade | F85: =Planejamento!D50 -> 0 | H85: =Planejamento!N50 -> 0
B86: =Planejamento!B51 -> pontos de automação | E86: =Planejamento!C51 -> unidade | F86: =Planejamento!D51 -> 0 | H86: =Planejamento!N51 -> 0
B87: =Planejamento!B52 -> pontos de automação para audio | E87: =Planejamento!C52 -> unidade | F87: =Planejamento!D52 -> 0 | H87: =Planejamento!N52 -> 0
B88: =Planejamento!B53 -> pontos de automação para luminárias | E88: =Planejamento!C53 -> unidade | F88: =Planejamento!D53 -> 0 | H88: =Planejamento!N53 -> 0
B89: =Planejamento!B54 -> pontos de automação para video | E89: =Planejamento!C54 -> unidade | F89: =Planejamento!D54 -> 0 | H89: =Planejamento!N54 -> 0
B90: =Planejamento!B55 -> quadro de automação | E90: =Planejamento!C55 -> unidade | F90: =Planejamento!D55 -> 0 | H90: =Planejamento!N55 -> 0
B91: =Planejamento!B56 -> retornos para automação | E91: =Planejamento!C56 -> unidade | F91: =Planejamento!D56 -> 0 | H91: =Planejamento!N56 -> 0
B93: HIDROSANITÁRIO | F93: =H93*100/(G199) -> 2.7638937 | G93: % | H93: =SUM(H97:H106) -> 791.044
E95: m² | ml | unid. | F95: quant.
B97: =Planejamento!B57 -> deslocamento de ponto de água quente ou fria | E97: =Planejamento!C57 -> unidade | F97: =Planejamento!D57 -> 0 | H97: =Planejamento!N57 -> 0
B98: =Planejamento!B58 -> deslocamento de ponto de esgoto para pia cozinha | E98: =Planejamento!C58 -> unidade | F98: =Planejamento!D58 -> 2 | H98: =Planejamento!N58 -> 791.044
B99: =Planejamento!B59 -> eliminar ponto de água quente ou fria | E99: =Planejamento!C59 -> unidade | F99: =Planejamento!D59 -> 0 | H99: =Planejamento!N59 -> 0
B100: =Planejamento!B60 -> eliminar ponto de esgoto | E100: =Planejamento!C60 -> unidade | F100: =Planejamento!D60 -> 0 | H100: =Planejamento!N60 -> 0
B101: =Planejamento!B61 -> instalação base para monocomando | E101: =Planejamento!C61 -> unidade | F101: =Planejamento!D61 -> 0 | H101: =Planejamento!N61 -> 0
B102: =Planejamento!B62 -> instalação de ralo linear quadrado | E102: =Planejamento!C62 -> unidade | F102: =Planejamento!D62 -> 0 | H102: =Planejamento!N62 -> 0
B103: =Planejamento!B63 -> instalação de ralo linear retangular | E103: =Planejamento!C63 -> unidade | F103: =Planejamento!D63 -> 0 | H103: =Planejamento!N63 -> 0
B104: =Planejamento!B64 -> instalação de registros | E104: =Planejamento!C64 -> unidade | F104: =Planejamento!D64 -> 0 | H104: =Planejamento!N64 -> 0
B105: =Planejamento!B65 -> novo ponto de água fria ou quente | E105: =Planejamento!C65 -> unidade | F105: =Planejamento!D65 -> 0 | H105: =Planejamento!N65 -> 0
B106: =Planejamento!B66 -> novo ponto de esgoto | E106: =Planejamento!C66 -> unidade | F106: =Planejamento!D66 -> 0 | H106: =Planejamento!N66 -> 0
B108: GÁS | F108: =H108*100/(G199) -> 0 | G108: % | H108: =SUM(H112) -> 0
E110: m² | ml | unid. | F110: quant.
B112: =Planejamento!B67 -> ponto de gás | E112: =Planejamento!C67 -> unidade | F112: =Planejamento!D67 -> 0 | H112: =Planejamento!N67 -> 0
B114: DRYWALL | F114: =H114*100/(G199) -> 0 | G114: % | H114: =SUM(H118:H133) -> 0
E116: m² | ml | unid. | F116: quant.
B118: =Planejamento!B68 -> colocação de moldura | E118: =Planejamento!C68 -> ml | F118: =Planejamento!D68 -> 0 | H118: =Planejamento!N68 -> 0
B119: =Planejamento!B69 -> cortineiro | E119: =Planejamento!C69 -> ml | F119: =Planejamento!D69 -> 0 | H119: =Planejamento!N69 -> 0
B120: =Planejamento!B70 -> fechamento de buracos | E120: =Planejamento!C70 -> unidade | F120: =Planejamento!D70 -> 0 | H120: =Planejamento!N70 -> 0
B121: =Planejamento!B71 -> forro | E121: =Planejamento!C71 -> m² | F121: =Planejamento!D71 -> 0 | H121: =Planejamento!N71 -> 0
B122: =Planejamento!B72 -> gesso negativo | E122: =Planejamento!C72 -> ml | F122: =Planejamento!D72 -> 0 | H122: =Planejamento!N72 -> 0
B123: =Planejamento!B73 -> Lã de Rocha Isofibras 2" c/6 unidades | E123: =Planejamento!C73 -> unidade | F123: =Planejamento!D73 -> 0 | H123: =Planejamento!N73 -> 0
B124: =Planejamento!B74 -> manta pet para acústica hidrosanitária | E124: =Planejamento!C74 -> unidade | F124: =Planejamento!D74 -> 0 | H124: =Planejamento!N74 -> 0
B125: =Planejamento!B75 -> nicho em drywall | E125: =Planejamento!C75 -> m² | F125: =Planejamento!D75 -> 0 | H125: =Planejamento!N75 -> 0
B126: =Planejamento!B76 -> parede drywall duas faces | E126: =Planejamento!C76 -> m² | F126: =Planejamento!D76 -> 0 | H126: =Planejamento!N76 -> 0
B127: =Planejamento!B77 -> parede drywall uma face | E127: =Planejamento!C77 -> m² | F127: =Planejamento!D77 -> 0 | H127: =Planejamento!N77 -> 0
B128: =Planejamento!B78 -> parede drywall placa verde duas faces | E128: =Planejamento!C78 -> m² | F128: =Planejamento!D78 -> 0 | H128: =Planejamento!N78 -> 0
B129: =Planejamento!B79 -> parede drywall placa verde uma face | E129: =Planejamento!C79 -> m² | F129: =Planejamento!D79 -> 0 | H129: =Planejamento!N79 -> 0
... B133: =Planejamento!B83 -> tabica | E133: =Planejamento!C83 -> ml | F133: =Planejamento!D83 -> 0 | H133: =Planejamento!N83 -> 0
B135: PAREDES | F135: =H135*100/(G199) -> 3.459704 | G135: % | H135: =SUM(H139:H151) -> 990.18933
E137: m² | ml | unid. | F137: quant.
...

Sheet Planejamento
D1: Venda | G1: Imposto | H1: Venda | I1: Compra
A2: Categoria | B2: Itens _ Descritivos | C2: m² | ml | unid. | hora | D2: Quant. | E2: Custo | F2: Quat.XCusto | G2: 0.1633 | H2: C/ Imposto | I2: Quant. | J2: Custo | K2: Total | L2: Rentabilidade | M2: 0.7 | N2: valor final
A3: Documentação | B3: Projeto Arquitetonito para Liberação da Obra | C3: m² | D3: 0 | E3: 40 | F3: =D3*E3 -> 0 | G3: =G2 -> 0.1633 | H3: =(F3*G3)+F3 -> 0 | I3: 0 | J3: 3 | K3: =I3*J3 -> 0 | L3: =N3-K3 -> 0 | M3: 0.1 | N3: =H3*M3+H3 -> 0
A4: Documentação | B4: Anotação de Responsabilidade Técnica (RRT) | C4: m² | D4: 36 | E4: 14.5 | F4: =D4*E4 -> 522 | G4: =G3 -> 0.1633 | H4: =(F4*G4)+F4 -> 607.2426 | I4: 1 | J4: 500 | K4: =I4*J4 -> 500 | L4: =N4-K4 -> 532.31242 | M4: =M2 -> 0.7 | N4: =H4*M4+H4 -> 1032.3124 | O4: =L4*1/N4 -> 0.5156505
A5: Documentação | B5: Impressões | C5: unidade | D5: 0 | E5: 3 | F5: =D5*E5 -> 0 | G5: =G4 -> 0.1633 | H5: =(F5*G5)+F5 -> 0 | I5: 0 | J5: 0 | K5: =I5*J5 -> 0 | L5: =N5-K5 -> 0 | M5: =M2 -> 0.7 | N5: =H5*M5+H5 -> 0
A6: Documentação | B6: Seguro de Obra | C6: m² | D6: 0 | E6: 8 | F6: =D6*E6 -> 0 | G6: =G5 -> 0.1633 | H6: =(F6*G6)+F6 -> 0 | I6: 0 | J6: 0 | K6: =I6*J6 -> 0 | L6: =N6-K6 -> 0 | M6: =M5 -> 0.7 | N6: =H6*M6+H6 -> 0
A7: Staff | B7: arquiteto | C7: hora | D7: 0 | E7: 110 | F7: =D7*E7 -> 0 | G7: =G6 -> 0.1633 | H7: =(F7*G7)+F7 -> 0 | I7: 0 | J7: 0 | K7: =I7*J7 -> 0 | L7: =N7-K7 -> 0 | M7: =M6 -> 0.7 | N7: =H7*M7+H7 -> 0
A8: Staff | B8: ajudante | C8: unidade | D8: 0 | E8: 80 | F8: =D8*E8 -> 0 | G8: =G7 -> 0.1633 | H8: =(F8*G8)+F8 -> 0 | I8: 0 | J8: 0 | K8: =I8*J8 -> 0 | L8: =N8-K8 -> 0 | M8: =M7 -> 0.7 | N8: =H8*M8+H8 -> 0
A9: Staff | B9: encarregado | C9: unidade | D9: 0 | E9: 40 | F9: =D9*E9 -> 0 | G9: =G8 -> 0.1633 | H9: =(F9*G9)+F9 -> 0 | I9: 0 | J9: 0 | K9: =I9*J9 -> 0 | L9: =N9-K9 -> 0 | M9: =M8 -> 0.7 | N9: =H9*M9+H9 -> 0
A10: Staff | B10: engenheiro | C10: unidade | D10: 0 | E10: 150 | F10: =D10*E10 -> 0 | G10: =G9 -> 0.1633 | H10: =(F10*G10)+F10 -> 0 | I10: 0 | J10: 0 | K10: =I10*J10 -> 0 | L10: =N10-K10 -> 0 | M10: =M9 -> 0.7 | N10: =H10*M10+H10 -> 0
A11: Staff | B11: limpeza recorrente | C11: unidade | D11: 36 | E11: 12 | F11: =D11*E11 -> 432 | G11: =G10 -> 0.1633 | H11: =(F11*G11)+F11 -> 502.5456 | I11: 0 | J11: 0 | K11: =I11*J11 -> 0 | L11: =N11-K11 -> 854.32752 | M11: =M10 -> 0.7 | N11: =H11*M11+H11 -> 854.32752 | O11: =L11*1/N11 -> 1
A12: Demolições | B12: saco para entulho* | C12: unidade | D12: 0 | E12: 2.5 | F12: =D12*E12 -> 0 | G12: =G11 -> 0.1633 | H12: =(F12*G12)+F12 -> 0 | I12: 0 | J12: 0 | K12: =I12*J12 -> 0 | L12: =N12-K12 -> 0 | M12: =M11 -> 0.7 | N12: =H12*M12+H12 -> 0
A13: Demolições | B13: demolição de alvenaria | C13: m² | D13: 0 | E13: 25 | F13: =D13*E13 -> 0 | G13: =G12 -> 0.1633 | H13: =(F13*G13)+F13 -> 0 | I13: 0 | J13: 0 | K13: =I13*J13 -> 0 | L13: =N13-K13 -> 0 | M13: =M12 -> 0.7 | N13: =H13*M13+H13 -> 0
A14: Demolições | B14: demolição e remocação de teto drywall | C14: m² | D14: 0 | E14: 45 | F14: =D14*E14 -> 0 | G14: =G13 -> 0.1633 | H14: =(F14*G14)+F14 -> 0 | I14: 0 | J14: 0 | K14: =I14*J14 -> 0 | L14: =N14-K14 -> 0 | M14: =M13 -> 0.7 | N14: =H14*M14+H14 -> 0
A15: Demolições | B15: equipe para retirada de entulho | C15: unidade | D15: 36 | E15: 15 | F15: =D15*E15 -> 540 | G15: =G14 -> 0.1633 | H15: =(F15*G15)+F15 -> 628.182 | I15: 0 | J15: 0 | K15: =I15*J15 -> 0 | L15: =N15-K15 -> 1067.9094 | M15: =M14 -> 0.7 | N15: =H15*M15+H15 -> 1067.9094 | O15: =L15*1/N15 -> 1
A16: Demolições | B16: caçamba de entulho* | C16: unidade | D16: 0 | E16: 300 | F16: =D16*E16 -> 0 | G16: =G15 -> 0.1633 | H16: =(F16*G16)+F16 -> 0 | I16: 0 | J16: 0 | K16: =I16*J16 -> 0 | L16: =N16-K16 -> 0 | M16: =M15 -> 0.7 | N16: =H16*M16+H16 -> 0
A17: remoções | B17: remoção de pisos | C17: unidade | D17: 0 | E17: 20 | F17: =D17*E17 -> 0 | G17: =G16 -> 0.1633 | H17: =(F17*G17)+F17 -> 0 | I17: 0 | J17: 0 | K17: =I17*J17 -> 0 | L17: =N17-K17 -> 0 | M17: =M16 -> 0.7 | N17: =H17*M17+H17 -> 0
A18: remoções | B18: remoção de caxilhos e portas | C18: unidade | D18: 0 | E18: 100 | F18: =D18*E18 -> 0 | G18: =G17 -> 0.1633 | H18: =(F18*G18)+F18 -> 0 | I18: 0 | J18: 0 | K18: =I18*J18 -> 0 | L18: =N18-K18 -> 0 | M18: =M17 -> 0.7 | N18: =H18*M18+H18 -> 0
A19: remoções | B19: remoções de portas e batentes | C19: unidade | D19: 0 | E19: 50 | F19: =D19*E19 -> 0 | G19: =G18 -> 0.1633 | H19: =(F19*G19)+F19 -> 0 | I19: 0 | J19: 0 | K19: =I19*J19 -> 0 | L19: =N19-K19 -> 0 | M19: =M18 -> 0.7 | N19: =H19*M19+H19 -> 0
A20: Remoções | B20: remoção de bancada de cozinha | C20: unidade | D20: 1 | E20: 100 | F20: =D20*E20 -> 100 | G20: =G19 -> 0.1633 | H20: =(F20*G20)+F20 -> 116.33 | I20: 0 | J20: 0 | K20: =I20*J20 -> 0 | L20: =N20-K20 -> 197.761 | M20: =M19 -> 0.7 | N20: =H20*M20+H20 -> 197.761 | O20: =L20*1/N20 -> 1
A21: Remoções | B21: remoção de tanque | C21: unidade | D21: 0 | E21: 40 | F21: =D21*E21 -> 0 | G21: =G20 -> 0.1633 | H21: =(F21*G21)+F21 -> 0 | I21: 0 | J21: 0 | K21: =I21*J21 -> 0 | L21: =N21-K21 -> 0 | M21: =M20 -> 0.7 | N21: =H21*M21+H21 -> 0
A22: Remoções | B22: remoção de bacias sanitárias | C22: unidade | D22: 0 | E22: 40 | F22: =D22*E22 -> 0 | G22: =G21 -> 0.1633 | H22: =(F22*G22)+F22 -> 0 | I22: 0 | J22: 0 | K22: =I22*J22 -> 0 | L22: =N22-K22 -> 0 | M22: =M21 -> 0.7 | N22: =H22*M22+H22 -> 0
A23: Remoções | B23: remoção de torneira | C23: unidade | D23: 0 | E23: 20 | F23: =D23*E23 -> 0 | G23: =G22 -> 0.1633 | H23: =(F23*G23)+F23 -> 0 | I23: 0 | J23: 0 | K23: =I23*J23 -> 0 | L23: =N23-K23 -> 0 | M23: =M22 -> 0.7 | N23: =H23*M23+H23 -> 0
A24: Remoções | B24: remoção de bancada de banheiro | C24: unidade | D24: 1 | E24: 100 | F24: =D24*E24 -> 100 | G24: =G23 -> 0.1633 | H24: =(F24*G24)+F24 -> 116.33 | I24: 0 | J24: 0 | K24: =I24*J24 -> 0 | L24: =N24-K24 -> 197.761 | M24: =M23 -> 0.7 | N24: =H24*M24+H24 -> 197.761 | O24: =L24*1/N24 -> 1
A25: Remoções | B25: armários com descarte | C25: unidade | D25: 0 | E25: 150 | F25: =D25*E25 -> 0 | G25: =G24 -> 0.1633 | H25: =(F25*G25)+F25 -> 0 | I25: 0 | J25: 0 | K25: =I25*J25 -> 0 | L25: =N25-K25 -> 0 | M25: =M24 -> 0.7 | N25: =H25*M25+H25 -> 0
A26: Infra Ar | B26: tubulação para equipamentos de 9 mil a 12 mil btus | C26: ml | D26: 10 | E26: 140 | F26: =D26*E26 -> 1400 | G26: =G25 -> 0.1633 | H26: =(F26*G26)+F26 -> 1628.62 | I26: 1 | J26: 800 | K26: =I26*J26 -> 800 | L26: =N26-K26 -> 1968.654 | M26: =M25 -> 0.7 | N26: =H26*M26+H26 -> 2768.654 | O26: =L26*1/N26 -> 0.71105093
A27: Infra Ar | B27: tubulação para equipamentos de 18 mil a 24 mil btus | C27: ml | D27: 0 | E27: 160 | F27: =D27*E27 -> 0 | G27: =G26 -> 0.1633 | H27: =(F27*G27)+F27 -> 0 | I27: 0 | J27: 0 | K27: =I27*J27 -> 0 | L27: =N27-K27 -> 0 | M27: =M26 -> 0.7 | N27: =H27*M27+H27 -> 0
A28: Infra Ar | B28: drenos | C28: unidade | D28: 1 | E28: 200 | F28: =D28*E28 -> 200 | G28: =G27 -> 0.1633 | H28: =(F28*G28)+F28 -> 232.66 | I28: 1 | J28: 150 | K28: =I28*J28 -> 150 | L28: =N28-K28 -> 245.522 | M28: =M27 -> 0.7 | N28: =H28*M28+H28 -> 395.522 | O28: =L28*1/N28 -> 0.62075434
A29: Infra Ar | B29: acoplamento dos equipamentos | C29: unidade | D29: 1 | E29: 300 | F29: =D29*E29 -> 300 | G29: =G28 -> 0.1633 | H29: =(F29*G29)+F29 -> 348.99 | I29: 1 | J29: 150 | K29: =I29*J29 -> 150 | L29: =N29-K29 -> 443.283 | M29: =M28 -> 0.7 | N29: =H29*M29+H29 -> 593.283 | O29: =L29*1/N29 -> 0.74716956
A30: Elétrica | B30: alteração de quadro elétrico | C30: unidade | D30: 0 | E30: 300 | F30: =D30*E30 -> 0 | G30: =G29 -> 0.1633 | H30: =(F30*G30)+F30 -> 0 | I30: 0 | J30: 0 | K30: =I30*J30 -> 0 | L30: =N30-K30 -> 0 | M30: =M29 -> 0.7 | N30: =H30*M30+H30 -> 0
A31: Elétrica | B31: instalação de balizador | C31: unidade | D31: 0 | E31: 40 | F31: =D31*E31 -> 0 | G31: =G30 -> 0.1633 | H31: =(F31*G31)+F31 -> 0 | I31: 0 | J31: 0 | K31: =I31*J31 -> 0 | L31: =N31-K31 -> 0 | M31: =M30 -> 0.7 | N31: =H31*M31+H31 -> 0
A32: Elétrica | B32: instalação de fita de led | C32: unidade | D32: 0 | E32: 60 | F32: =D32*E32 -> 0 | G32: =G31 -> 0.1633 | H32: =(F32*G32)+F32 -> 0 | I32: 0 | J32: 0 | K32: =I32*J32 -> 0 | L32: =N32-K32 -> 0 | M32: =M31 -> 0.7 | N32: =H32*M32+H32 -> 0
A33: Elétrica | B33: instalação de luminárias especiais | C33: unidade | D33: 0 | E33: 40 | F33: =D33*E33 -> 0 | G33: =G32 -> 0.1633 | H33: =(F33*G33)+F33 -> 0 | I33: 0 | J33: 0 | K33: =I33*J33 -> 0 | L33: =N33-K33 -> 0 | M33: =M32 -> 0.7 | N33: =H33*M33+H33 -> 0
A34: Elétrica | B34: instalação de lustre | C34: unidade | D34: 0 | E34: 40 | F34: =D34*E34 -> 0 | G34: =G33 -> 0.1633 | H34: =(F34*G34)+F34 -> 0 | I34: 0 | J34: 0 | K34: =I34*J34 -> 0 | L34: =N34-K34 -> 0 | M34: =M33 -> 0.7 | N34: =H34*M34+H34 -> 0
A35: Elétrica | B35: instalação de pendente | C35: unidade | D35: 0 | E35: 50 | F35: =D35*E35 -> 0 | G35: =G34 -> 0.1633 | H35: =(F35*G35)+F35 -> 0 | I35: 0 | J35: 0 | K35: =I35*J35 -> 0 | L35: =N35-K35 -> 0 | M35: =M34 -> 0.7 | N35: =H35*M35+H35 -> 0
A36: Elétrica | B36: interruptor intermediário | C36: unidade | D36: 0 | E36: 40 | F36: =D36*E36 -> 0 | G36: =G35 -> 0.1633 | H36: =(F36*G36)+F36 -> 0 | I36: 0 | J36: 0 | K36: =I36*J36 -> 0 | L36: =N36-K36 -> 0 | M36: =M35 -> 0.7 | N36: =H36*M36+H36 -> 0
A37: Elétrica | B37: interruptor paralelo | C37: unidade | D37: 0 | E37: 30 | F37: =D37*E37 -> 0 | G37: =G36 -> 0.1633 | H37: =(F37*G37)+F37 -> 0 | I37: 0 | J37: 0 | K37: =I37*J37 -> 0 | L37: =N37-K37 -> 0 | M37: =M36 -> 0.7 | N37: =H37*M37+H37 -> 0
A38: Elétrica | B38: interruptor simples | C38: unidade | D38: 0 | E38: 25 | F38: =D38*E38 -> 0 | G38: =G37 -> 0.1633 | H38: =(F38*G38)+F38 -> 0 | I38: 0 | J38: 0 | K38: =I38*J38 -> 0 | L38: =N38-K38 -> 0 | M38: =M37 -> 0.7 | N38: =H38*M38+H38 -> 0
A39: Elétrica | B39: ponto de balizador | C39: unidade | D39: 0 | E39: 40 | F39: =D39*E39 -> 0 | G39: =G38 -> 0.1633 | H39: =(F39*G39)+F39 -> 0 | I39: 0 | J39: 0 | K39: =I39*J39 -> 0 | L39: =N39-K39 -> 0 | M39: =M38 -> 0.7 | N39: =H39*M39+H39 -> 0
A40: Elétrica | B40: ponto de energia para motorização | C40: unidade | D40: 0 | E40: 40 | F40: =D40*E40 -> 0 | G40: =G39 -> 0.1633 | H40: =(F40*G40)+F40 -> 0 | I40: 0 | J40: 0 | K40: =I40*J40 -> 0 | L40: =N40-K40 -> 0 | M40: =M39 -> 0.7 | N40: =H40*M40+H40 -> 0
A41: Elétrica | B41: furação e recorte para luminárias | C41: unidade | D41: 0 | E41: 18 | F41: =D41*E41 -> 0 | G41: =G40 -> 0.1633 | H41: =(F41*G41)+F41 -> 0 | I41: 0 | J41: 0 | K41: =I41*J41 -> 0 | L41: =N41-K41 -> 0 | M41: =M40 -> 0.7 | N41: =H41*M41+H41 -> 0
A42: Elétrica | B42: instalação de luminárias | C42: unidade | D42: 12 | E42: 50 | F42: =D42*E42 -> 600 | G42: =G41 -> 0.1633 | H42: =(F42*G42)+F42 -> 697.98 | I42: 12 | J42: 40 | K42: =I42*J42 -> 480 | L42: =N42-K42 -> 706.566 | M42: =M41 -> 0.7 | N42: =H42*M42+H42 -> 1186.566 | O42: =L42*1/N42 -> 0.5954713
A43: Elétrica | B43: ponto de iluminação | C43: unidade | D43: 2 | E43: 120 | F43: =D43*E43 -> 240 | G43: =G42 -> 0.1633 | H43: =(F43*G43)+F43 -> 279.192 | I43: 2 | J43: 60 | K43: =I43*J43 -> 120 | L43: =N43-K43 -> 354.6264 | M43: =M42 -> 0.7 | N43: =H43*M43+H43 -> 474.6264 | O43: =L43*1/N43 -> 0.74716956
A44: Elétrica | B44: ponto de tomada 110v | C44: unidade | D44: 0 | E44: 35 | F44: =D44*E44 -> 0 | G44: =G43 -> 0.1633 | H44: =(F44*G44)+F44 -> 0 | I44: 0 | J44: 0 | K44: =I44*J44 -> 0 | L44: =N44-K44 -> 0 | M44: =M43 -> 0.7 | N44: =H44*M44+H44 -> 0
A45: Elétrica | B45: ponto de tomada 220v | C45: unidade | D45: 0 | E45: 45 | F45: =D45*E45 -> 0 | G45: =G44 -> 0.1633 | H45: =(F45*G45)+F45 -> 0 | I45: 0 | J45: 0 | K45: =I45*J45 -> 0 | L45: =N45-K45 -> 0 | M45: =M44 -> 0.7 | N45: =H45*M45+H45 -> 0
A46: Elétrica | B46: ponto de tomada 220v circuito independente | C46: unidade | D46: 0 | E46: 75 | F46: =D46*E46 -> 0 | G46: =G45 -> 0.1633 | H46: =(F46*G46)+F46 -> 0 | I46: 0 | J46: 0 | K46: =I46*J46 -> 0 | L46: =N46-K46 -> 0 | M46: =M45 -> 0.7 | N46: =H46*M46+H46 -> 0
A47: Elétrica | B47: ponto para led | C47: unidade | D47: 1 | E47: 100 | F47: =D47*E47 -> 100 | G47: =G46 -> 0.1633 | H47: =(F47*G47)+F47 -> 116.33 | I47: 2 | J47: 35 | K47: =I47*J47 -> 70 | L47: =N47-K47 -> 127.761 | M47: =M46 -> 0.7 | N47: =H47*M47+H47 -> 197.761 | O47: =L47*1/N47 -> 0.64603739
A48: Automação | B48: ponto de internet | C48: unidade | D48: 0 | E48: 35 | F48: =D48*E48 -> 0 | G48: =G47 -> 0.1633 | H48: =(F48*G48)+F48 -> 0 | I48: 0 | J48: 0 | K48: =I48*J48 -> 0 | L48: =N48-K48 -> 0 | M48: =M47 -> 0.7 | N48: =H48*M48+H48 -> 0
A49: Automação | B49: ponto de som | C49: unidade | D49: 0 | E49: 38 | F49: =D49*E49 -> 0 | G49: =G48 -> 0.1633 | H49: =(F49*G49)+F49 -> 0 | I49: 0 | J49: 0 | K49: =I49*J49 -> 0 | L49: =N49-K49 -> 0 | M49: =M48 -> 0.7 | N49: =H49*M49+H49 -> 0
A50: Automação | B50: ponto de wifi | C50: unidade | D50: 0 | E50: 35 | F50: =D50*E50 -> 0 | G50: =G49 -> 0.1633 | H50: =(F50*G50)+F50 -> 0 | I50: 0 | J50: 0 | K50: =I50*J50 -> 0 | L50: =N50-K50 -> 0 | M50: =M49 -> 0.7 | N50: =H50*M50+H50 -> 0
A51: Automação | B51: pontos de automação | C51: unidade | D51: 0 | E51: 70 | F51: =D51*E51 -> 0 | G51: =G50 -> 0.1633 | H51: =(F51*G51)+F51 -> 0 | I51: 0 | J51: 0 | K51: =I51*J51 -> 0 | L51: =N51-K51 -> 0 | M51: =M50 -> 0.7 | N51: =H51*M51+H51 -> 0
A52: Automação | B52: pontos de automação para audio | C52: unidade | D52: 0 | E52: 70 | F52: =D52*E52 -> 0 | G52: =G51 -> 0.1633 | H52: =(F52*G52)+F52 -> 0 | I52: 0 | J52: 0 | K52: =I52*J52 -> 0 | L52: =N52-K52 -> 0 | M52: =M51 -> 0.7 | N52: =H52*M52+H52 -> 0
A53: Automação | B53: pontos de automação para luminárias | C53: unidade | D53: 0 | E53: 70 | F53: =D53*E53 -> 0 | G53: =G52 -> 0.1633 | H53: =(F53*G53)+F53 -> 0 | I53: 0 | J53: 0 | K53: =I53*J53 -> 0 | L53: =N53-K53 -> 0 | M53: =M52 -> 0.7 | N53: =H53*M53+H53 -> 0
A54: Automação | B54: pontos de automação para video | C54: unidade | D54: 0 | E54: 70 | F54: =D54*E54 -> 0 | G54: =G53 -> 0.1633 | H54: =(F54*G54)+F54 -> 0 | I54: 0 | J54: 0 | K54: =I54*J54 -> 0 | L54: =N54-K54 -> 0 | M54: =M53 -> 0.7 | N54: =H54*M54+H54 -> 0
A55: Automação | B55: quadro de automação | C55: unidade | D55: 0 | E55: 1100 | F55: =D55*E55 -> 0 | G55: =G54 -> 0.1633 | H55: =(F55*G55)+F55 -> 0 | I55: 0 | J55: 0 | K55: =I55*J55 -> 0 | L55: =N55-K55 -> 0 | M55: =M54 -> 0.7 | N55: =H55*M55+H55 -> 0
A56: Automação | B56: retornos para automação | C56: unidade | D56: 0 | E56: 70 | F56: =D56*E56 -> 0 | G56: =G55 -> 0.1633 | H56: =(F56*G56)+F56 -> 0 | I56: 0 | J56: 0 | K56: =I56*J56 -> 0 | L56: =N56-K56 -> 0 | M56: =M55 -> 0.7 | N56: =H56*M56+H56 -> 0
A57: Hidrossanitária | B57: deslocamento de ponto de água quente ou fria | C57: unidade | D57: 0 | E57: 40 | F57: =D57*E57 -> 0 | G57: =G56 -> 0.1633 | H57: =(F57*G57)+F57 -> 0 | I57: 0 | J57: 0 | K57: =I57*J57 -> 0 | L57: =N57-K57 -> 0 | M57: =M56 -> 0.7 | N57: =H57*M57+H57 -> 0
A58: Hidrossanitária | B58: deslocamento de ponto de esgoto para pia cozinha | C58: unidade | D58: 2 | E58: 200 | F58: =D58*E58 -> 400 | G58: =G57 -> 0.1633 | H58: =(F58*G58)+F58 -> 465.32 | I58: 2 | J58: 100 | K58: =I58*J58 -> 200 | L58: =N58-K58 -> 591.044 | M58: =M57 -> 0.7 | N58: =H58*M58+H58 -> 791.044 | O58: =L58*1/N58 -> 0.74716956
A59: Hidrossanitária | B59: eliminar ponto de água quente ou fria | C59: unidade | D59: 0 | E59: 30 | F59: =D59*E59 -> 0 | G59: =G58 -> 0.1633 | H59: =(F59*G59)+F59 -> 0 | I59: 0 | J59: 0 | K59: =I59*J59 -> 0 | L59: =N59-K59 -> 0 | M59: =M58 -> 0.7 | N59: =H59*M59+H59 -> 0
A60: Hidrossanitária | B60: eliminar ponto de esgoto | C60: unidade | D60: 0 | E60: 30 | F60: =D60*E60 -> 0 | G60: =G59 -> 0.1633 | H60: =(F60*G60)+F60 -> 0 | I60: 0 | J60: 0 | K60: =I60*J60 -> 0 | L60: =N60-K60 -> 0 | M60: =M59 -> 0.7 | N60: =H60*M60+H60 -> 0
A61: Hidrossanitária | B61: instalação base para monocomando | C61: unidade | D61: 0 | E61: 90 | F61: =D61*E61 -> 0 | G61: =G60 -> 0.1633 | H61: =(F61*G61)+F61 -> 0 | I61: 0 | J61: 0 | K61: =I61*J61 -> 0 | L61: =N61-K61 -> 0 | M61: =M60 -> 0.7 | N61: =H61*M61+H61 -> 0
A62: Hidrossanitária | B62: instalação de ralo linear quadrado | C62: unidade | D62: 0 | E62: 50 | F62: =D62*E62 -> 0 | G62: =G61 -> 0.1633 | H62: =(F62*G62)+F62 -> 0 | I62: 0 | J62: 0 | K62: =I62*J62 -> 0 | L62: =N62-K62 -> 0 | M62: =M61 -> 0.7 | N62: =H62*M62+H62 -> 0
A63: Hidrossanitária | B63: instalação de ralo linear retangular | C63: unidade | D63: 0 | E63: 40 | F63: =D63*E63 -> 0 | G63: =G62 -> 0.1633 | H63: =(F63*G63)+F63 -> 0 | I63: 0 | J63: 0 | K63: =I63*J63 -> 0 | L63: =N63-K63 -> 0 | M63: =M62 -> 0.7 | N63: =H63*M63+H63 -> 0
A64: Hidrossanitária | B64: instalação de registros | C64: unidade | D64: 0 | E64: 40 | F64: =D64*E64 -> 0 | G64: =G63 -> 0.1633 | H64: =(F64*G64)+F64 -> 0 | I64: 0 | J64: 0 | K64: =I64*J64 -> 0 | L64: =N64-K64 -> 0 | M64: =M63 -> 0.7 | N64: =H64*M64+H64 -> 0
A65: Hidrossanitária | B65: novo ponto de água fria ou quente | C65: unidade | D65: 0 | E65: 100 | F65: =D65*E65 -> 0 | G65: =G64 -> 0.1633 | H65: =(F65*G65)+F65 -> 0 | I65: 0 | J65: 0 | K65: =I65*J65 -> 0 | L65: =N65-K65 -> 0 | M65: =M64 -> 0.7 | N65: =H65*M65+H65 -> 0
A66: Hidrossanitária | B66: novo ponto de esgoto | C66: unidade | D66: 0 | E66: 80 | F66: =D66*E66 -> 0 | G66: =G65 -> 0.1633 | H66: =(F66*G66)+F66 -> 0 | I66: 0 | J66: 0 | K66: =I66*J66 -> 0 | L66: =N66-K66 -> 0 | M66: =M65 -> 0.7 | N66: =H66*M66+H66 -> 0
A67: gás | B67: ponto de gás | C67: unidade | D67: 0 | E67: 150 | F67: =D67*E67 -> 0 | G67: =G66 -> 0.1633 | H67: =(F67*G67)+F67 -> 0 | I67: 0 | J67: 0 | K67: =I67*J67 -> 0 | L67: =N67-K67 -> 0 | M67: =M66 -> 0.7 | N67: =H67*M67+H67 -> 0
A68: Gesso | B68: colocação de moldura | C68: ml | D68: 0 | E68: 25 | F68: =D68*E68 -> 0 | G68: =G67 -> 0.1633 | H68: =(F68*G68)+F68 -> 0 | I68: 0 | J68: 0 | K68: =I68*J68 -> 0 | L68: =N68-K68 -> 0 | M68: =M67 -> 0.7 | N68: =H68*M68+H68 -> 0
A69: Gesso | B69: cortineiro | C69: ml | D69: 0 | E69: 50 | F69: =D69*E69 -> 0 | G69: =G68 -> 0.1633 | H69: =(F69*G69)+F69 -> 0 | I69: 0 | J69: 0 | K69: =I69*J69 -> 0 | L69: =N69-K69 -> 0 | M69: =M68 -> 0.7 | N69: =H69*M69+H69 -> 0
A70: Gesso | B70: fechamento de buracos | C70: unidade | D70: 0 | E70: 15 | F70: =D70*E70 -> 0 | G70: =G69 -> 0.1633 | H70: =(F70*G70)+F70 -> 0 | I70: 0 | J70: 0 | K70: =I70*J70 -> 0 | L70: =N70-K70 -> 0 | M70: =M69 -> 0.7 | N70: =H70*M70+H70 -> 0
... A95: Paredes | B95: assentamento de revestimentos mosaicos | C95: m² | D95: 0 | E95: 55 | F95: =D95*E95 -> 0 | G95: =G94 -> 0.1633 | H95: =(F95*G95)+F95 -> 0 | I95: 0 | J95: 0 | K95: =I95*J95 -> 0 | L95: =N95-K95 -> 0 | M95: =M94 -> 0.7 | N95: =H95*M95+H95 -> 0
A96: Paredes | B96: assentamento de revestimentos especiais | C96: m² | D96: =1.21+0.72+0.52+1.48*0.6 -> 3.338 | E96: 150 | F96: =D96*E96 -> 500.7 | G96: =G95 -> 0.1633 | H96: =(F96*G96)+F96 -> 582.46431 | I96: 3.33 | J96: 100 | K96: =I96*J96 -> 333 | L96: =N96-K96 -> 657.18933 | M96: =M95 -> 0.7 | N96: =H96*M96+H96 -> 990.18933 | O96: =L96*1/N96 -> 0.66370068
A97: Piso | B97: colocação de piso vinilico com rodapé branco mdf 7 cm | C97: m² | D97: =11.1+9.96+5.27 -> 26.33 | E97: 110 | F97: =D97*E97 -> 2896.3 | G97: =G96 -> 0.1633 | H97: =(F97*G97)+F97 -> 3369.2658 | I97: 1 | J97: 4183.33 | K97: 4018 | L97: =N97-K97 -> 2009.7518 | M97: =M96 -> 0.7 | N97: =H97*M97+H97+300 -> 6027.7518 | O97: =L97*1/N97 -> 0.33341649
A98: Piso | B98: contrapiso | C98: m² | D98: =11.1+9.96+5.27 -> 26.33 | E98: 35 | F98: =D98*E98 -> 921.55 | G98: =G97 -> 0.1633 | H98: =(F98*G98)+F98 -> 1072.0391 | I98: 1 | J98: 1200 | K98: =I98*J98 -> 1200 | L98: =N98-K98 -> 622.4665 | M98: =M97 -> 0.7 | N98: =H98*M98+H98 -> 1822.4665 | O98: =L98*1/N98 -> 0.34155168 | R98: Custo Cubas | S98: Custo | T98: Rentabilidade
A99: Piso | B99: assentamento de porcelanato até 90x90 | C99: m² | D99: 0 | E99: 65 | F99: =D99*E99 -> 0 | G99: =G98 -> 0.1633 | H99: =(F99*G99)+F99 -> 0 | I99: 0 | J99: 0 | K99: =I99*J99 -> 0 | L99: =N99-K99 -> 0 | M99: =M98 -> 0.7 | N99: =H99*M99+H99 -> 0
A100: Piso | B100: assentamento de porcelanato até 100x100 a 120x120 | C100: m² | D100: 0 | E100: 60 | F100: =D100*E100 -> 0 | G100: =G99 -> 0.1633 | H100: =(F100*G100)+F100 -> 0 | I100: 0 | J100: 0 | K100: =I100*J100 -> 0 | L100: =N100-K100 -> 0 | M100: =M99 -> 0.7 | N100: =H100*M100+H100 -> 0
A101: Piso | B101: base de alvenaria | C101: m² | D101: 0 | E101: 80 | F101: =D101*E101 -> 0 | G101: =G100 -> 0.1633 | H101: =(F101*G101)+F101 -> 0 | I101: 0 | J101: 0 | K101: =I101*J101 -> 0 | L101: =N101-K101 -> 0 | M101: =M100 -> 0.7 | N101: =H101*M101+H101 -> 0
A102: Piso | B102: impermeabilização de piso | C102: m² | D102: 0 | E102: 15 | F102: =D102*E102 -> 0 | G102: =G101 -> 0.1633 | H102: =(F102*G102)+F102 -> 0 | I102: 0 | J102: 0 | K102: =I102*J102 -> 0 | L102: =N102-K102 -> 0 | M102: =M101 -> 0.7 | N102: =H102*M102+H102 -> 0
A103: Pintura | B103: emassar teto | C103: m² | D103: 0 | E103: 20 | F103: =D103*E103 -> 0 | G103: =G102 -> 0.1633 | H103: =(F103*G103)+F103 -> 0 | I103: 0 | J103: 0 | K103: =I103*J103 -> 0 | L103: =N103-K103 -> 0 | M103: =M102 -> 0.7 | N103: =H103*M103+H103 -> 0
A104: Pintura | B104: equipe de pintura para preparação | C104: m² | D104: 0 | E104: 5 | F104: =D104*E104 -> 0 | G104: =G103 -> 0.1633 | H104: =(F104*G104)+F104 -> 0 | I104: 0 | J104: 0 | K104: =I104*J104 -> 0 | L104: =N104-K104 -> 0 | M104: =M103 -> 0.7 | N104: =H104*M104+H104 -> 0
A105: Pintura | B105: equipe de pintura | C105: m² | D105: 0 | E105: 40 | F105: =D105*E105 -> 0 | G105: =G104 -> 0.1633 | H105: =(F105*G105)+F105 -> 0 | I105: 0 | J105: 0 | K105: =I105*J105 -> 0 | L105: =N105-K105 -> 0 | M105: =M104 -> 0.7 | N105: =H105*M105+H105 -> 0
A106: Pintura | B106: pintura de porta | C106: unidade | D106: 0 | E106: 120 | F106: =D106*E106 -> 0 | G106: =G105 -> 0.1633 | H106: =(F106*G106)+F106 -> 0 | I106: 0 | J106: 0 | K106: =I106*J106 -> 0 | L106: =N106-K106 -> 0 | M106: =M105 -> 0.7 | N106: =H106*M106+H106 -> 0
A107: Finalização | B107: Envidraçamento de Sacada | C107: m² | D107: 0 | E107: 900 | F107: =D107*E107 -> 0 | G107: =G106 -> 0.1633 | H107: =(F107*G107)+F107 -> 0 | I107: 0 | J107: 0 | K107: =I107*J107 -> 0 | L107: =N107-K107 -> 0 | M107: 0.3 | N107: =H107*M107+H107 -> 0
A108: Finalização | B108: bancada slim cozinha 1 - cuba pequena inox para tanque | C108: m² | D108: =1.21*0.6 -> 0.726 | E108: 2500 | F108: =D108*E108 -> 1815 | G108: =G107 -> 0.1633 | H108: =(F108*G108)+F108 -> 2111.3895 | I108: 1 | J108: =594.26+245.33+74.16+235.3+219.9 -> 1368.95 | K108: =I108*J108 -> 1368.95 | L108: =N108-K108 -> 1375.8564 | M108: =M107 -> 0.3 | N108: =H108*M108+H108 -> 2744.8064 | O108: =L108*1/N108 -> 0.50125808 | R108: 590.77 | S108: =SUM(K108:K110) -> 3846.8 | T108: =SUM(L108:L110)-R108 -> 2711.781
A109: Finalização | B109: bancada slim cozinha 2 - cuba pequena inox para pia cozinha | C109: m² | D109: =1.48*0.5 -> 0.74 | E109: 2500 | F109: =D109*E109 -> 1850 | G109: =G108 -> 0.1633 | H109: =(F109*G109)+F109 -> 2152.105 | I109: 1 | J109: =594.26+245.33+369.11+74.16+115.9 -> 1398.76 | K109: =I109*J109 -> 1398.76 | L109: =N109-K109 -> 1398.9765 | M109: =M108 -> 0.3 | N109: =H109*M109+H109 -> 2797.7365 | O109: =L109*1/N109 -> 0.50003869
A110: Finalização | B110: bancada slim banheiro - com cuba ceramica de apoio | C110: m² | D110: =0.85*0.5 -> 0.425 | E110: 2500 | F110: =D110*E110 -> 1062.5 | G110: =G109 -> 0.1633 | H110: =(F110*G110)+F110 -> 1236.0062 | I110: 1 | J110: =815.92+74.17+189 -> 1079.09 | K110: =I110*J110 -> 1079.09 | L110: =N110-K110 -> 527.71812 | M110: =M109 -> 0.3 | N110: =H110*M110+H110 -> 1606.8081 | O110: =L110*1/N110 -> 0.32842635
A111: Finalização | B111: Box Banheiro 0,90 X 2,10 | C111: unidade | D111: 1 | E111: 1200 | F111: =D111*E111 -> 1200 | G111: =G110 -> 0.1633 | H111: =(F111*G111)+F111 -> 1395.96 | I111: 1 | J111: 1400 | K111: =I111*J111 -> 1400 | L111: =N111-K111 -> 414.748 | M111: =M110 -> 0.3 | N111: =H111*M111+H111 -> 1814.748 | O111: =L111*1/N111 -> 0.22854303
A112: Finalização | B112: Espelho Banheiro 0,85 X 1,20 | C112: unidade | D112: 1 | E112: 700 | F112: =D112*E112 -> 700 | G112: =G111 -> 0.1633 | H112: =(F112*G112)+F112 -> 814.31 | I112: 1 | J112: 400 | K112: =I112*J112 -> 400 | L112: =N112-K112 -> 658.603 | M112: =M111 -> 0.3 | N112: =H112*M112+H112 -> 1058.603 | O112: =L112*1/N112 -> 0.62214352
A113: Finalização | B113: instalação de chuveiro | C113: unidade | D113: 0 | E113: 100 | F113: =D113*E113 -> 0 | G113: =G112 -> 0.1633 | H113: =(F113*G113)+F113 -> 0 | I113: 0 | J113: 0 | K113: =I113*J113 -> 0 | L113: =N113-K113 -> 0 | M113: =M112 -> 0.3 | N113: =H113*M113+H113 -> 0
A114: Finalização | B114: instalação de ducha higiênica | C114: unidade | D114: 0 | E114: 50 | F114: =D114*E114 -> 0 | G114: =G113 -> 0.1633 | H114: =(F114*G114)+F114 -> 0 | I114: 0 | J114: 0 | K114: =I114*J114 -> 0 | L114: =N114-K114 -> 0 | M114: =M113 -> 0.3 | N114: =H114*M114+H114 -> 0
A115: Finalização | B115: instalação de fechadura eletrônica | C115: unidade | D115: 0 | E115: 250 | F115: =D115*E115 -> 0 | G115: =G114 -> 0.1633 | H115: =(F115*G115)+F115 -> 0 | I115: 0 | J115: 0 | K115: =I115*J115 -> 0 | L115: =N115-K115 -> 0 | M115: =M114 -> 0.3 | N115: =H115*M115+H115 -> 0
A116: Finalização | B116: instalação de metais - porta papel higiênico | C116: unidade | D116: 0 | E116: 150 | F116: =D116*E116 -> 0 | G116: =G115 -> 0.1633 | H116: =(F116*G116)+F116 -> 0 | I116: 0 | J116: 0 | K116: =I116*J116 -> 0 | L116: =N116-K116 -> 0 | M116: =M115 -> 0.3 | N116: =H116*M116+H116 -> 0
A117: Finalização | B117: instalação de metais - toalheiro | C117: unidade | D117: 0 | E117: 150 | F117: =D117*E117 -> 0 | G117: =G116 -> 0.1633 | H117: =(F117*G117)+F117 -> 0 | I117: 0 | J117: 0 | K117: =I117*J117 -> 0 | L117: =N117-K117 -> 0 | M117: =M116 -> 0.3 | N117: =H117*M117+H117 -> 0
A118: Finalização | B118: Instalação de rodapé | C118: ml | D118: 0 | E118: 30 | F118: =D118*E118 -> 0 | G118: =G117 -> 0.1633 | H118: =(F118*G118)+F118 -> 0 | I118: 0 | J118: 0 | K118: =I118*J118 -> 0 | L118: =N118-K118 -> 0 | M118: =M117 -> 0.3 | N118: =H118*M118+H118 -> 0
A119: Finalização | B119: instalação de torneiras duplo comando | C119: unidade | D119: 0 | E119: 80 | F119: =D119*E119 -> 0 | G119: =G118 -> 0.1633 | H119: =(F119*G119)+F119 -> 0 | I119: 0 | J119: 0 | K119: =I119*J119 -> 0 | L119: =N119-K119 -> 0 | M119: =M118 -> 0.3 | N119: =H119*M119+H119 -> 0
A120: Finalização | B120: instalação de torneiras monocomando | C120: unidade | D120: 0 | E120: 60 | F120: =D120*E120 -> 0 | G120: =G119 -> 0.1633 | H120: =(F120*G120)+F120 -> 0 | I120: 0 | J120: 0 | K120: =I120*J120 -> 0 | L120: =N120-K120 -> 0 | M120: =M119 -> 0.3 | N120: =H120*M120+H120 -> 0
A121: Limpeza | B121: Limpeza pós Obra Especializada | C121: m² | D121: 0 | E121: 15 | F121: =D121*E121 -> 0 | G121: =G120 -> 0.1633 | H121: =(F121*G121)+F121 -> 0 | I121: 0 | J121: 0 | K121: =I121*J121 -> 0 | L121: =N121-K121 -> 0 | M121: =M120 -> 0.3 | N121: =H121*M121+H121 -> 0
F123: =SUM(F3:F121) -> 15880.05 | K123: 0 | L123: =SUM(L4:L112) -> 14952.837 | N123: =SUM(N3:N121) -> 28620.637
F124: 0.3 | H124: =SUM(F123:F125) -> 20644.365 | I124: 0.32 | J124: =H124*I124 -> 6606.1968 | K124: =H124+J124 -> 27250.562
F125: =F123*F124 -> 4764.015

Sheet Piso Vinilico 
L2: Unid. | M2: Quant. | N2: Caixas | O2: Valor | P2: Total
C3: Piso Vinilico: | D3: Angelin Pedra | K3: PISO LVT AGIFLOOR VINILICO (3.0 MM) (0,50MM) 3,611 M2 - 8010 ANGELIN PEDRA NEW 18,5 X 122 | L3: M² | M3: 32.499 | N3: 9 | O3: 75.15 | P3: =M3*O3 -> 2442.2999
K4: ADESIVO AGI 4 KG | L4: Kg | M4: 12 | N4: 3 | O4: 29.88 | P4: =M4*O4 -> 358.56
C5: Ambiente | D5: Medida | F5: m² | K5: Cola HOMESTAR Nova Formula 1 kg | L5: Unid. | M5: 2 | N5: 2 | O5: 26.5 | P5: =M5*O5 -> 53
K6: RODAPE 15 CM 2,16 ML - BRANCO MAX FRISADO | L6: ml | M6: 17.28 | N6: 8 | O6: 19.53 | P6: =M6*O6 -> 337.4784
C7: Sala | D7: 2.45 | E7: 4.55 | F7: =D7*E7 -> 11.1475 | P7: =SUM(P3:P6) -> 3191.3383
C8: Dorm 1 | D8: 4 | E8: 2.5 | F8: =D8*E8 -> 10 | K8: frete | P8: =176.99+40 -> 216.99
C9: Dorm 2 | D9: 2 | E9: 2.65 | F9: =D9*E9 -> 5.3 | K9: instalação piso | L9: m² | M9: 25 | O9: 20 | P9: =M9*O9 -> 500
E10: Total | F10: =SUM(F7:F9) -> 26.4475 | K10: instalação rodapé | M10: 10 | O10: 11 | P10: =M10*O10 -> 110
F11: 0.1
F12: =F10*F11+F10 -> 29.09225 | H12: 72.9 | I12: =F12*H12 -> 2120.825 | P12: =SUM(P7:P10) -> 4018.3283
P13: =P12/32.5 -> 123.64087
C14: Cola Piso | D14: R$
K15: Cobrar Diferença do Cliente R$ 337,48
C18: Rodapé: | D18: branco 15cm
D19: Medida Linear | F19: ML
C20: Total | F20: =17.64-3 -> 14.64
F21: 0.1
F22: =F20*F21+F20 -> 16.104
C24: Fixadores | D24: R$
C25: Cola | D25: R$
C28: Mão de Obra
E29: Piso | F29: Rodapé
C30: Instalação

Sheet Extras
D4: Marmoraria
A5: Não foi vendido pintura para o cliente
A6: Orçar pintura
A7: Orçar Cotineiro de gesso
A9: Shaft para esconder tubulações | B9: 550
